sakit/__init__.py
sakit/birdeye.py
sakit/dflow_prediction.py
sakit/image_gen.py
sakit/jupiter_holdings.py
sakit/jupiter_recurring.py
sakit/jupiter_shield.py
sakit/jupiter_token_search.py
sakit/jupiter_trigger.py
sakit/mcp.py
sakit/privy_create_user.py
sakit/privy_create_wallet.py
sakit/privy_dflow_prediction.py
sakit/privy_dflow_swap.py
sakit/privy_get_user_by_telegram.py
sakit/privy_privacy_cash.py
sakit/privy_recurring.py
sakit/privy_transfer.py
sakit/privy_trigger.py
sakit/privy_ultra.py
sakit/privy_ultra_quote.py
sakit/privy_wallet_address.py
sakit/rugcheck.py
sakit/search_internet.py
sakit/solana_dflow_swap.py
sakit/solana_transfer.py
sakit/solana_ultra.py
sakit/solana_ultra_quote.py
sakit/technical_analysis.py
sakit/token_math.py
sakit/utils/dflow.py
sakit/utils/recurring.py
sakit/utils/transfer.py
sakit/utils/trigger.py
sakit/utils/ultra.py
sakit/utils/wallet.py
sakit/vybe.py
sakit-18.0.1.dist-info/METADATA
sakit-18.0.1.dist-info/WHEEL
sakit-18.0.1.dist-info/entry_points.txt
sakit-18.0.1.dist-info/licenses/LICENSE
sakit-18.0.1.dist-info/RECORD
