Metadata-Version: 2.4
Name: sakit
Version: 18.0.1
Summary: Solana Agent Kit
License: MIT
License-File: LICENSE
Keywords: ai,openai,ai agents,agi
Author: Bevan Hunt
Author-email: bevan@bevanhunt.com
Requires-Python: >=3.13,<3.14
Classifier: License :: OSI Approved :: MIT License
Classifier: Programming Language :: Python :: 3
Classifier: Programming Language :: Python :: 3.13
Classifier: Programming Language :: Python :: 3 :: Only
Classifier: Topic :: Scientific/Engineering :: Artificial Intelligence
Requires-Dist: based58 (>=0.1.1,<0.2.0)
Requires-Dist: boto3 (>=1.42.29,<2.0.0)
Requires-Dist: botocore (>=1.42.29,<2.0.0)
Requires-Dist: fastmcp (>=2.14.3,<3.0.0)
Requires-Dist: httpx (>=0.28.1,<0.29.0)
Requires-Dist: openai
Requires-Dist: pandas-ta (>=0.4.71b0,<0.5.0)
Requires-Dist: privy-client (>=0.5.0,<0.6.0)
Requires-Dist: pynacl (>=1.6.2,<2.0.0)
Requires-Dist: solana (>=0.36.11,<0.37.0)
Requires-Dist: solana-agent (>=33.0.0)
Requires-Dist: solders (>=0.27.1,<0.28.0)
Project-URL: Repository, https://github.com/truemagic-coder/solana-agent-kit
